pixoo_ng/__init__.py
pixoo_ng/_colors.py
pixoo_ng/api.py
pixoo_ng/config.py
pixoo_ng/exceptions.py
pixoo_ng/find_device.py
pixoo_ng/font.py
pixoo_ng/simulator.py
pixoo_ng-1.0.0.dist-info/LICENSE
pixoo_ng-1.0.0.dist-info/METADATA
pixoo_ng-1.0.0.dist-info/WHEEL
pixoo_ng-1.0.0.dist-info/top_level.txt
pixoo_ng-1.0.0.dist-info/RECORD
